{
    "uuid": "5f350f71-14bf-4f3a-98cc-a5536e81fc85",
    "url": "http://www.songkick.com/artists/236156-elysian-fields",
    "scrape_json": {
        "@context": "http://schema.org",
        "@type": "MusicEvent",
        "name": "Elysian Fields",
        "url": "https://www.songkick.com/concerts/40540322-elysian-fields-at-ubu?utm_medium=organic&utm_source=microformat",
        "image": "media/profile_images/artists/236156/huge_avatar",
        "location": {
            "@type": "Place",
            "address": {
                "@type": "PostalAddress",
                "addressLocality": "Rennes",
                "addressCountry": "France",
                "streetAddress": "1, Rue Saint-Helier",
                "postalCode": "35000"
            },
            "name": "Ubu",
            "sameAs": "http://www.ubu-rennes.com",
            "geo": {
                "@type": "GeoCoordinates",
                "latitude": 48.10797,
                "longitude": -1.67256
            }
        },
        "eventStatus": "https://schema.org/EventScheduled",
        "startDate": "2022-09-25T17:00:00+0200",
        "endDate": "2022-09-25",
        "performer": [
            {
                "@type": "MusicGroup",
                "name": "Elysian Fields",
                "sameAs": "https://www.songkick.com/artists/236156-elysian-fields?utm_medium=organic&utm_source=microformat"
            }
        ],
        "description": "Elysian Fields at Ubu at 2022-09-25T17:00:00+0200",
        "offers": [
            {
                "@type": "Offer",
                "url": "http://www.songkick.com/concerts/40540322-elysian-fields-at-ubu?utm_medium=organic&utm_source=microformat"
            }
        ]
    },
    "elapsed": 2.221228837966919
}